{
  "idea_id": "yzz00182",
  "title": "高铁动车组保洁交路脚本",
  "fields": {
    "日期": "2026-06-01",
    "任务类型": "0-1代码生成",
    "业务领域": "自动化与工具脚本",
    "修改范围": "模块内多文件",
    "形态": "自动化脚本",
    "核心场景": "业务人员要对高铁动车组保洁交路过程中的关键记录做准入判断、差异提示和结果归档",
    "关键机制": "明细导出、时间窗口限制、处理建议生成、批量任务状态、指标分级",
    "避免相似": "只处理高铁动车组保洁交路，不写成万能数据清洗程序",
    "提示词": "实现一个用于业务人员要对高铁动车组保洁交路过程中的关键记录做准入判断、差异提示和结果归档的脚本。输入业务记录、问题字典、去重键和报表模板后，输出统计结果、异常样本、趋势摘要和导出文件；时间窗口、分组维度和阈值命中需可解释。用低风险、中风险、高风险、无法判定验证，确保状态、原因、导出结果和历史轨迹保持一致。"
  },
  "prompt_source": "idea-history:提示词",
  "workspace": "/Users/bill/Documents/solo/workspaces/yzz00182"
}